lib/__init__.py
lib/adhyan.py
Topsis_adhyan_102103695-0.0.1.dist-info/METADATA
Topsis_adhyan_102103695-0.0.1.dist-info/WHEEL
Topsis_adhyan_102103695-0.0.1.dist-info/top_level.txt
Topsis_adhyan_102103695-0.0.1.dist-info/RECORD
